{"dependencies":[{"name":"../components/Icon.vue","loc":{"line":1,"column":17}}],"generated":{"js":"\"use strict\";\n\nvar _Icon = require(\"../components/Icon.vue\");\n\nvar _Icon2 = _interopRequireDefault(_Icon);\n\nfunction _interopRequireDefault(obj) { return obj && obj.__esModule ? obj : { default: obj }; }\n\n_Icon2.default.register({ \"paper-plane\": { \"width\": 1792, \"height\": 1792, \"paths\": [{ \"d\": \"M1764 11q33 24 27 64l-256 1536q-5 29-32 45-14 8-31 8-11 0-24-5l-453-185-242 295q-18 23-49 23-13 0-22-4-19-7-30.5-23.5t-11.5-36.5v-349l864-1059-1069 925-395-162q-37-14-40-55-2-40 32-59l1664-960q15-9 32-9 20 0 36 11z\" }] } });"},"hash":"91833b91818a14ae47dd01cb93965027"}