{"dependencies":[{"name":"../components/Icon.vue","loc":{"line":1,"column":17}}],"generated":{"js":"\"use strict\";\n\nvar _Icon = require(\"../components/Icon.vue\");\n\nvar _Icon2 = _interopRequireDefault(_Icon);\n\nfunction _interopRequireDefault(obj) { return obj && obj.__esModule ? obj : { default: obj }; }\n\n_Icon2.default.register({ \"pencil\": { \"width\": 1536, \"height\": 1792, \"paths\": [{ \"d\": \"M363 1536l91-91-235-235-91 91v107h128v128h107zM886 608q0-22-22-22-10 0-17 7l-542 542q-7 7-7 17 0 22 22 22 10 0 17-7l542-542q7-7 7-17zM832 416l416 416-832 832h-416v-416zM1515 512q0 53-37 90l-166 166-416-416 166-165q36-38 90-38 53 0 91 38l235 234q37 39 37 91z\" }] } });"},"hash":"53638f3da39cabfbaf0a9be65734dfce"}